[
  {
    "id": 1759627167188,
    "user_id": 1,
    "title": "VAMOS VOAR!!!!!!!",
    "content": "🌟 {mensagem_motivacional}\r\n\r\n#motivacao #sucesso #mindset",
    "hashtags": "",
    "template": "Post Motivacional",
    "platforms": "[]",
    "image_url": "/uploads/image-1759627167149-763592633.jpg",
    "customization": "{\"font\":\"font-inter\",\"color\":\"#1f2937\",\"background\":\"gradient-1\",\"textEffect\":\"normal\"}",
    "status": "draft",
    "created_at": "2025-10-05T01:19:27.188Z"
  }
]